{
    "model_id": "constrained",
    "areas": [
        { "is_supplemental": true, "label": "b1" },
        { "is_supplemental": true, "label": "b2" },
        { "is_supplemental": false, "label": "a1" },
        { "is_supplemental": false, "label": "a2" },
        { "is_supplemental": false, "label": "a3" },
        { "is_supplemental": false, "label": "a4" }
    ],
    "traits": [
        { "nstates": 2, "transition_rate": 0.062247, "label": "habitat" }
    ],
    "diversification": {
        "mean_birth_rate" : 0.05486829846551938,
        "mean_death_rate" : 0.0
    },
    "anagenetic_range_evolution": {
        "global_area_gain_rate": 0.018156246,
        "lineage_area_gain_weight": {
            "definition_type": "trait_state_index_map:habitat",
            "definition": [ 1.0, 0.0 ]
        },
        "mean_area_loss_rate": 0.00257819
    },
    "termination_conditions": {
        "target_focal_area_lineages": 365
    }
}
